{
    "date": "2024-10-13",
    "export_timestamp": "2026-06-01 21:04:22",
    "point_count": 35,
    "reduction_percent": 93,
    "positions": [
        {
            "time": "2024-10-13T00:00:00Z",
            "lat": 38.7271667,
            "lon": 16.9818233
        },
        {
            "time": "2024-10-13T00:14:00Z",
            "lat": 38.7139167,
            "lon": 16.9647083
        },
        {
            "time": "2024-10-13T00:19:00Z",
            "lat": 38.7088733,
            "lon": 16.9587333
        },
        {
            "time": "2024-10-13T00:20:00Z",
            "lat": 38.7081033,
            "lon": 16.9572033
        },
        {
            "time": "2024-10-13T00:26:00Z",
            "lat": 38.7014833,
            "lon": 16.9492817
        },
        {
            "time": "2024-10-13T01:21:00Z",
            "lat": 38.6304633,
            "lon": 16.8592933
        },
        {
            "time": "2024-10-13T01:24:00Z",
            "lat": 38.6265917,
            "lon": 16.8540333
        },
        {
            "time": "2024-10-13T01:26:00Z",
            "lat": 38.6251817,
            "lon": 16.8498267
        },
        {
            "time": "2024-10-13T01:28:00Z",
            "lat": 38.622215,
            "lon": 16.847005
        },
        {
            "time": "2024-10-13T01:31:00Z",
            "lat": 38.61832,
            "lon": 16.8417767
        },
        {
            "time": "2024-10-13T01:32:00Z",
            "lat": 38.6172567,
            "lon": 16.8398567
        },
        {
            "time": "2024-10-13T01:34:00Z",
            "lat": 38.6142817,
            "lon": 16.8368917
        },
        {
            "time": "2024-10-13T01:49:00Z",
            "lat": 38.5942017,
            "lon": 16.811745
        },
        {
            "time": "2024-10-13T01:55:00Z",
            "lat": 38.5867417,
            "lon": 16.8056183
        },
        {
            "time": "2024-10-13T02:06:00Z",
            "lat": 38.5748867,
            "lon": 16.7931383
        },
        {
            "time": "2024-10-13T02:19:00Z",
            "lat": 38.562485,
            "lon": 16.780705
        },
        {
            "time": "2024-10-13T02:26:00Z",
            "lat": 38.5539817,
            "lon": 16.774975
        },
        {
            "time": "2024-10-13T02:33:00Z",
            "lat": 38.5449533,
            "lon": 16.7694317
        },
        {
            "time": "2024-10-13T02:34:00Z",
            "lat": 38.5437883,
            "lon": 16.7683917
        },
        {
            "time": "2024-10-13T05:28:00Z",
            "lat": 38.3889067,
            "lon": 16.561805
        },
        {
            "time": "2024-10-13T06:40:00Z",
            "lat": 38.33832,
            "lon": 16.4763217
        },
        {
            "time": "2024-10-13T06:46:00Z",
            "lat": 38.3344551,
            "lon": 16.4713126
        },
        {
            "time": "2024-10-13T06:56:00Z",
            "lat": 38.3287683,
            "lon": 16.4610783
        },
        {
            "time": "2024-10-13T07:16:00Z",
            "lat": 38.3230636,
            "lon": 16.4391473
        },
        {
            "time": "2024-10-13T07:18:00Z",
            "lat": 38.3228517,
            "lon": 16.435775
        },
        {
            "time": "2024-10-13T07:20:00Z",
            "lat": 38.32302,
            "lon": 16.4324317
        },
        {
            "time": "2024-10-13T07:21:00Z",
            "lat": 38.3233973,
            "lon": 16.4308728
        },
        {
            "time": "2024-10-13T07:22:00Z",
            "lat": 38.3242516,
            "lon": 16.4297411
        },
        {
            "time": "2024-10-13T07:23:00Z",
            "lat": 38.3251533,
            "lon": 16.430075
        },
        {
            "time": "2024-10-13T07:25:00Z",
            "lat": 38.3260267,
            "lon": 16.4320167
        },
        {
            "time": "2024-10-13T07:27:00Z",
            "lat": 38.3271883,
            "lon": 16.433595
        },
        {
            "time": "2024-10-13T07:29:00Z",
            "lat": 38.3279167,
            "lon": 16.4354867
        },
        {
            "time": "2024-10-13T07:31:00Z",
            "lat": 38.3287218,
            "lon": 16.4356413
        },
        {
            "time": "2024-10-13T16:48:07Z",
            "lat": 38.3286773,
            "lon": 16.4362193
        },
        {
            "time": "2024-10-13T17:54:00Z",
            "lat": 38.3289117,
            "lon": 16.4362243
        }
    ]
}