{
    "date": "2025-09-04",
    "export_timestamp": "2026-06-01 21:04:29",
    "point_count": 15,
    "reduction_percent": 86,
    "positions": [
        {
            "time": "2025-09-04T00:00:00Z",
            "lat": 38.792424,
            "lon": 20.854449
        },
        {
            "time": "2025-09-04T07:27:00Z",
            "lat": 38.790897,
            "lon": 20.856049
        },
        {
            "time": "2025-09-04T07:38:00Z",
            "lat": 38.780888,
            "lon": 20.871905
        },
        {
            "time": "2025-09-04T07:44:00Z",
            "lat": 38.778348,
            "lon": 20.87907
        },
        {
            "time": "2025-09-04T07:45:00Z",
            "lat": 38.777847,
            "lon": 20.879694
        },
        {
            "time": "2025-09-04T07:46:00Z",
            "lat": 38.777359,
            "lon": 20.879737
        },
        {
            "time": "2025-09-04T07:49:00Z",
            "lat": 38.778226,
            "lon": 20.879672
        },
        {
            "time": "2025-09-04T07:51:00Z",
            "lat": 38.778002,
            "lon": 20.880008
        },
        {
            "time": "2025-09-04T07:54:00Z",
            "lat": 38.777966,
            "lon": 20.879034
        },
        {
            "time": "2025-09-04T07:57:00Z",
            "lat": 38.777611,
            "lon": 20.878679
        },
        {
            "time": "2025-09-04T08:03:00Z",
            "lat": 38.777376,
            "lon": 20.878809
        },
        {
            "time": "2025-09-04T12:28:11Z",
            "lat": 38.777404,
            "lon": 20.878436
        },
        {
            "time": "2025-09-04T13:30:26Z",
            "lat": 38.77745,
            "lon": 20.878322
        },
        {
            "time": "2025-09-04T20:49:00Z",
            "lat": 38.77749,
            "lon": 20.878804
        },
        {
            "time": "2025-09-04T23:00:00Z",
            "lat": 38.777458,
            "lon": 20.878766
        }
    ]
}