{
    "date": "2025-08-13",
    "export_timestamp": "2026-06-01 21:04:29",
    "point_count": 48,
    "reduction_percent": 90,
    "positions": [
        {
            "time": "2025-08-13T00:00:00Z",
            "lat": 38.359012,
            "lon": 21.419641
        },
        {
            "time": "2025-08-13T06:42:00Z",
            "lat": 38.359154,
            "lon": 21.420012
        },
        {
            "time": "2025-08-13T06:43:00Z",
            "lat": 38.359169,
            "lon": 21.419681
        },
        {
            "time": "2025-08-13T06:44:00Z",
            "lat": 38.358015,
            "lon": 21.419935
        },
        {
            "time": "2025-08-13T06:47:00Z",
            "lat": 38.354188,
            "lon": 21.421547
        },
        {
            "time": "2025-08-13T06:48:00Z",
            "lat": 38.352771,
            "lon": 21.421494
        },
        {
            "time": "2025-08-13T07:07:00Z",
            "lat": 38.318668,
            "lon": 21.414266
        },
        {
            "time": "2025-08-13T07:08:00Z",
            "lat": 38.316782,
            "lon": 21.413722
        },
        {
            "time": "2025-08-13T07:09:00Z",
            "lat": 38.316178,
            "lon": 21.411897
        },
        {
            "time": "2025-08-13T08:07:00Z",
            "lat": 38.287994,
            "lon": 21.308155
        },
        {
            "time": "2025-08-13T09:08:00Z",
            "lat": 38.279307,
            "lon": 21.203346
        },
        {
            "time": "2025-08-13T09:09:00Z",
            "lat": 38.279175,
            "lon": 21.201243
        },
        {
            "time": "2025-08-13T09:11:00Z",
            "lat": 38.279561,
            "lon": 21.196643
        },
        {
            "time": "2025-08-13T09:12:00Z",
            "lat": 38.27933,
            "lon": 21.194527
        },
        {
            "time": "2025-08-13T09:17:00Z",
            "lat": 38.276043,
            "lon": 21.184583
        },
        {
            "time": "2025-08-13T09:33:00Z",
            "lat": 38.267184,
            "lon": 21.152538
        },
        {
            "time": "2025-08-13T09:41:00Z",
            "lat": 38.263985,
            "lon": 21.138234
        },
        {
            "time": "2025-08-13T09:49:00Z",
            "lat": 38.25947,
            "lon": 21.12147
        },
        {
            "time": "2025-08-13T09:51:00Z",
            "lat": 38.258764,
            "lon": 21.117937
        },
        {
            "time": "2025-08-13T09:53:00Z",
            "lat": 38.258716,
            "lon": 21.113792
        },
        {
            "time": "2025-08-13T10:24:00Z",
            "lat": 38.262791,
            "lon": 21.053205
        },
        {
            "time": "2025-08-13T10:31:00Z",
            "lat": 38.265902,
            "lon": 21.040231
        },
        {
            "time": "2025-08-13T10:32:00Z",
            "lat": 38.266632,
            "lon": 21.03883
        },
        {
            "time": "2025-08-13T10:33:00Z",
            "lat": 38.267515,
            "lon": 21.03805
        },
        {
            "time": "2025-08-13T10:36:00Z",
            "lat": 38.268076,
            "lon": 21.036004
        },
        {
            "time": "2025-08-13T11:28:00Z",
            "lat": 38.293836,
            "lon": 20.91833
        },
        {
            "time": "2025-08-13T11:29:00Z",
            "lat": 38.294354,
            "lon": 20.916903
        },
        {
            "time": "2025-08-13T11:34:00Z",
            "lat": 38.29775,
            "lon": 20.912064
        },
        {
            "time": "2025-08-13T11:41:00Z",
            "lat": 38.303436,
            "lon": 20.902131
        },
        {
            "time": "2025-08-13T13:36:00Z",
            "lat": 38.389815,
            "lon": 20.733199
        },
        {
            "time": "2025-08-13T13:39:00Z",
            "lat": 38.392055,
            "lon": 20.726208
        },
        {
            "time": "2025-08-13T13:42:00Z",
            "lat": 38.393561,
            "lon": 20.718949
        },
        {
            "time": "2025-08-13T13:43:00Z",
            "lat": 38.393689,
            "lon": 20.716537
        },
        {
            "time": "2025-08-13T13:45:00Z",
            "lat": 38.392105,
            "lon": 20.711946
        },
        {
            "time": "2025-08-13T13:48:00Z",
            "lat": 38.388799,
            "lon": 20.705704
        },
        {
            "time": "2025-08-13T13:50:00Z",
            "lat": 38.386185,
            "lon": 20.701886
        },
        {
            "time": "2025-08-13T13:51:00Z",
            "lat": 38.384455,
            "lon": 20.700843
        },
        {
            "time": "2025-08-13T13:52:00Z",
            "lat": 38.382495,
            "lon": 20.700478
        },
        {
            "time": "2025-08-13T13:53:00Z",
            "lat": 38.38054,
            "lon": 20.700536
        },
        {
            "time": "2025-08-13T13:54:00Z",
            "lat": 38.378771,
            "lon": 20.70154
        },
        {
            "time": "2025-08-13T13:58:00Z",
            "lat": 38.372803,
            "lon": 20.70822
        },
        {
            "time": "2025-08-13T13:59:00Z",
            "lat": 38.371122,
            "lon": 20.709558
        },
        {
            "time": "2025-08-13T14:02:00Z",
            "lat": 38.368144,
            "lon": 20.710649
        },
        {
            "time": "2025-08-13T14:05:00Z",
            "lat": 38.367535,
            "lon": 20.712018
        },
        {
            "time": "2025-08-13T14:06:00Z",
            "lat": 38.367748,
            "lon": 20.71201
        },
        {
            "time": "2025-08-13T15:00:00Z",
            "lat": 38.36763,
            "lon": 20.712423
        },
        {
            "time": "2025-08-13T19:30:19Z",
            "lat": 38.367787,
            "lon": 20.71204
        },
        {
            "time": "2025-08-13T23:00:00Z",
            "lat": 38.367731,
            "lon": 20.712034
        }
    ]
}