{
    "date": "2025-09-03",
    "export_timestamp": "2026-06-01 21:04:29",
    "point_count": 36,
    "reduction_percent": 83,
    "positions": [
        {
            "time": "2025-09-03T00:00:00Z",
            "lat": 38.700858,
            "lon": 20.709566
        },
        {
            "time": "2025-09-03T07:05:00Z",
            "lat": 38.700966,
            "lon": 20.709185
        },
        {
            "time": "2025-09-03T07:14:00Z",
            "lat": 38.701123,
            "lon": 20.709614
        },
        {
            "time": "2025-09-03T07:31:00Z",
            "lat": 38.700846,
            "lon": 20.709978
        },
        {
            "time": "2025-09-03T08:00:00Z",
            "lat": 38.700571,
            "lon": 20.709785
        },
        {
            "time": "2025-09-03T08:48:10Z",
            "lat": 38.700775,
            "lon": 20.709315
        },
        {
            "time": "2025-09-03T08:50:00Z",
            "lat": 38.701511,
            "lon": 20.709828
        },
        {
            "time": "2025-09-03T08:51:00Z",
            "lat": 38.702611,
            "lon": 20.711123
        },
        {
            "time": "2025-09-03T08:53:00Z",
            "lat": 38.705199,
            "lon": 20.713201
        },
        {
            "time": "2025-09-03T08:57:00Z",
            "lat": 38.709631,
            "lon": 20.720811
        },
        {
            "time": "2025-09-03T09:05:00Z",
            "lat": 38.719,
            "lon": 20.733262
        },
        {
            "time": "2025-09-03T09:06:00Z",
            "lat": 38.719892,
            "lon": 20.733824
        },
        {
            "time": "2025-09-03T09:08:00Z",
            "lat": 38.722303,
            "lon": 20.73142
        },
        {
            "time": "2025-09-03T09:09:00Z",
            "lat": 38.722633,
            "lon": 20.731884
        },
        {
            "time": "2025-09-03T09:11:00Z",
            "lat": 38.722736,
            "lon": 20.73618
        },
        {
            "time": "2025-09-03T09:15:00Z",
            "lat": 38.724044,
            "lon": 20.743748
        },
        {
            "time": "2025-09-03T09:19:00Z",
            "lat": 38.726523,
            "lon": 20.752472
        },
        {
            "time": "2025-09-03T09:23:00Z",
            "lat": 38.729726,
            "lon": 20.760662
        },
        {
            "time": "2025-09-03T09:30:00Z",
            "lat": 38.736738,
            "lon": 20.775131
        },
        {
            "time": "2025-09-03T09:32:00Z",
            "lat": 38.738365,
            "lon": 20.779644
        },
        {
            "time": "2025-09-03T09:34:00Z",
            "lat": 38.740551,
            "lon": 20.783939
        },
        {
            "time": "2025-09-03T09:36:00Z",
            "lat": 38.741909,
            "lon": 20.788242
        },
        {
            "time": "2025-09-03T09:41:00Z",
            "lat": 38.746397,
            "lon": 20.798165
        },
        {
            "time": "2025-09-03T09:46:00Z",
            "lat": 38.751385,
            "lon": 20.807797
        },
        {
            "time": "2025-09-03T09:51:00Z",
            "lat": 38.755675,
            "lon": 20.814599
        },
        {
            "time": "2025-09-03T09:53:00Z",
            "lat": 38.757818,
            "lon": 20.817968
        },
        {
            "time": "2025-09-03T09:56:00Z",
            "lat": 38.761879,
            "lon": 20.823075
        },
        {
            "time": "2025-09-03T09:59:00Z",
            "lat": 38.763148,
            "lon": 20.825989
        },
        {
            "time": "2025-09-03T10:01:00Z",
            "lat": 38.764027,
            "lon": 20.827144
        },
        {
            "time": "2025-09-03T10:13:00Z",
            "lat": 38.780846,
            "lon": 20.844052
        },
        {
            "time": "2025-09-03T10:16:00Z",
            "lat": 38.78538,
            "lon": 20.847673
        },
        {
            "time": "2025-09-03T10:19:00Z",
            "lat": 38.789357,
            "lon": 20.852393
        },
        {
            "time": "2025-09-03T10:20:00Z",
            "lat": 38.790828,
            "lon": 20.853731
        },
        {
            "time": "2025-09-03T10:22:00Z",
            "lat": 38.792671,
            "lon": 20.854551
        },
        {
            "time": "2025-09-03T10:30:00Z",
            "lat": 38.792355,
            "lon": 20.854681
        },
        {
            "time": "2025-09-03T23:00:00Z",
            "lat": 38.792401,
            "lon": 20.854331
        }
    ]
}